<?xml version="1.0" encoding="UTF-8"?>
<objects serializationModel="Studio.02.02.00">
	<object class="AudioFile" id="{9f128c7a-7adb-4b8b-b348-2daac102240a}">
		<property name="assetPath">
			<value>Fire, Whoosh, Fireball, Big, Distorted 01 SND8717.wav</value>
		</property>
		<property name="frequencyInKHz">
			<value>96</value>
		</property>
		<property name="channelCount">
			<value>2</value>
		</property>
		<property name="length">
			<value>2.8497812499999999</value>
		</property>
		<relationship name="masterAssetFolder">
			<destination>{8a5edba4-144c-42e7-8442-0d26ba1b56f6}</destination>
		</relationship>
	</object>
</objects>
